pyqode.cobol-2.11.0-py3.5-nspkg.pth
pyqode/cobol/__init__.py
pyqode/cobol/_forms/__init__.py
pyqode/cobol/_forms/resources_rc.py
pyqode/cobol/api/__init__.py
pyqode/cobol/api/folding.py
pyqode/cobol/api/icons.py
pyqode/cobol/api/keywords.py
pyqode/cobol/api/pic.py
pyqode/cobol/api/regex.py
pyqode/cobol/api/parsers/__init__.py
pyqode/cobol/api/parsers/names.py
pyqode/cobol/api/parsers/pic.py
pyqode/cobol/backend/__init__.py
pyqode/cobol/backend/server.py
pyqode/cobol/backend/workers.py
pyqode/cobol/modes/__init__.py
pyqode/cobol/modes/auto_indent.py
pyqode/cobol/modes/backspace.py
pyqode/cobol/modes/comments.py
pyqode/cobol/modes/goto.py
pyqode/cobol/modes/indenter.py
pyqode/cobol/modes/margins.py
pyqode/cobol/modes/pic_offset.py
pyqode/cobol/modes/sh.py
pyqode/cobol/widgets/__init__.py
pyqode/cobol/widgets/code_edit.py
pyqode/cobol/widgets/outline.py
pyqode/cobol/widgets/pic_offsets.py
pyqode.cobol-2.11.0.dist-info/DESCRIPTION.rst
pyqode.cobol-2.11.0.dist-info/METADATA
pyqode.cobol-2.11.0.dist-info/RECORD
pyqode.cobol-2.11.0.dist-info/WHEEL
pyqode.cobol-2.11.0.dist-info/metadata.json
pyqode.cobol-2.11.0.dist-info/namespace_packages.txt
pyqode.cobol-2.11.0.dist-info/top_level.txt
