Metadata-Version: 1.1
Name: pyqode.cobol
Version: 2.11.0
Summary: Adds COBOL support to pyqode.core
Home-page: https://github.com/pyQode/pyqode.cobol
Author: Colin Duquesnoy
Author-email: colin.duquesnoy@gmail.com
License: MIT
Keywords: CodeEdit PySide PyQt code editor widget cobol
Platform: UNKNOWN
Classifier: Development Status :: 5 - Production/Stable
Classifier: Environment :: X11 Applications :: Qt
Classifier: Environment :: Win32 (MS Windows)
Classifier: Intended Audience :: Developers
Classifier: License :: OSI Approved :: MIT License
Classifier: Operating System :: Microsoft :: Windows
Classifier: Operating System :: POSIX :: Linux
Classifier: Programming Language :: Python :: 3.2
Classifier: Programming Language :: Python :: 3.3
Classifier: Programming Language :: Python :: 3.4
Classifier: Topic :: Software Development :: Libraries :: Application Frameworks
Classifier: Topic :: Software Development :: Widget Sets
Classifier: Topic :: Text Editors :: Integrated Development Environments (IDE)
